[
  {
    "text": "adios",
    "intent": "despedida",
    "intent_prediction": {
      "name": "agradecimiento",
      "confidence": 0.8712446689605713
    }
  },
  {
    "text": "buenas noches",
    "intent": "saludo",
    "intent_prediction": {
      "name": "despedida",
      "confidence": 0.9979794025421143
    }
  },
  {
    "text": "Buenos noches Aerito",
    "intent": "saludo",
    "intent_prediction": {
      "name": "despedida",
      "confidence": 0.9149360060691833
    }
  },
  {
    "text": "buenas noches",
    "intent": "despedida",
    "intent_prediction": {
      "name": "saludo",
      "confidence": 0.9999991655349731
    }
  },
  {
    "text": "Hi",
    "intent": "saludo",
    "intent_prediction": {
      "name": "faq",
      "confidence": 0.9751073122024536
    }
  },
  {
    "text": "Holis",
    "intent": "saludo",
    "intent_prediction": {
      "name": "faq",
      "confidence": 1.0
    }
  },
  {
    "text": "ok, si estoy dentro del plazo, gracias",
    "intent": "agradecimiento",
    "intent_prediction": {
      "name": "faq",
      "confidence": 0.9998406171798706
    }
  },
  {
    "text": "como realizo mi matricula",
    "intent": "matricula_procedimiento",
    "intent_prediction": {
      "name": "faq",
      "confidence": 1.0
    }
  },
  {
    "text": "cual es proceso de matricula",
    "intent": "faq",
    "intent_prediction": {
      "name": "matricula_procedimiento",
      "confidence": 0.9923170804977417
    }
  },
  {
    "text": "chau",
    "intent": "despedida",
    "intent_prediction": {
      "name": "agradecimiento",
      "confidence": 0.9976398348808289
    }
  },
  {
    "text": "cual es proceso de matricula",
    "intent": "matricula_procedimiento",
    "intent_prediction": {
      "name": "faq",
      "confidence": 1.0
    }
  }
]