[
  {
    "text": "hasta luego Aerito",
    "intent": "despedida",
    "intent_prediction": {
      "name": "saludo",
      "confidence": 0.83778977394104
    }
  },
  {
    "text": "Holis",
    "intent": "saludo",
    "intent_prediction": {
      "name": "despedida",
      "confidence": 0.6799457669258118
    }
  },
  {
    "text": "tengo otra duda",
    "intent": "confirmar_requerir_mas_ayuda",
    "intent_prediction": {
      "name": "denegar_mas_ayuda",
      "confidence": 0.4931379556655884
    }
  },
  {
    "text": "¿Hasta cuando puedo realizar el pago?",
    "intent": "pago_fechas",
    "intent_prediction": {
      "name": "procedimiento_tramites_fechas",
      "confidence": 0.8307254314422607
    }
  },
  {
    "text": "una consulta soy alumno regular de matematicas me indicaron que debo hacer unos pagos e ingresar a una plataforma para hacer mi matricula pero no entendi bien",
    "intent": "matricula__procedimiento_alumno_regular",
    "intent_prediction": {
      "name": "reserva_matricula__procedimiento",
      "confidence": 0.7157514095306396
    }
  },
  {
    "text": "una consulta soy alumno ingresante de matematicas me indicaron que debo hacer unos pagos e ingresar a una plataforma para hacer mi matricula pero no entendi bien",
    "intent": "matricula__procedimiento_alumno_ingresante",
    "intent_prediction": {
      "name": "reserva_matricula__procedimiento",
      "confidence": 0.8071013689041138
    }
  },
  {
    "text": "acabo de ingresar este ciclo, cuales son los pagos que debo hacer para la matricula",
    "intent": "matricula__procedimiento_alumno_ingresante",
    "intent_prediction": {
      "name": "matricula_procedimiento",
      "confidence": 0.30645543336868286
    }
  },
  {
    "text": "Hola Aerito, me puedes decir donde encontrar el cronograma de matricula",
    "intent": "matricula__cronograma",
    "intent_prediction": {
      "name": "matricula__horarios",
      "confidence": 0.42706865072250366
    }
  },
  {
    "text": "quiero saber en que horario debo ingresar para mi matricula",
    "intent": "matricula__horarios",
    "intent_prediction": {
      "name": "matricula__cronograma",
      "confidence": 0.4323970377445221
    }
  },
  {
    "text": "¿Cuando se puede pagar el autoseguro?",
    "intent": "pago_autoseguro__fechas",
    "intent_prediction": {
      "name": "pago_autoseguro_procedimiento",
      "confidence": 0.7410064935684204
    }
  },
  {
    "text": "Tengo una consulta sobre la matrícula dado que el día de hoy realize el pago de autoseguro, puedo matricularme de forma normal o paso a rezagado",
    "intent": "pago_autoseguro__fuera_fecha",
    "intent_prediction": {
      "name": "perdida_turno_matricula",
      "confidence": 0.2882722020149231
    }
  },
  {
    "text": "perdi mi turno para matricularme como procedo",
    "intent": "perdida_turno_matricula",
    "intent_prediction": {
      "name": "matricula_rezagada__procedimiento",
      "confidence": 0.5735669136047363
    }
  },
  {
    "text": "hola, dime para la matricula rezagada debo pagar ?",
    "intent": "matricula_rezagada__procedimiento",
    "intent_prediction": {
      "name": "reserva_matricula__procedimiento",
      "confidence": 0.6376736164093018
    }
  },
  {
    "text": "Buenas quiero cambiarme el horario del curso de biología es posible?",
    "intent": "cambio_seccion",
    "intent_prediction": {
      "name": "matricula__horarios",
      "confidence": 0.8208412528038025
    }
  },
  {
    "text": "Hola, no logro encontrar los horarios de los cursos donde estas ?",
    "intent": "cursos_horarios",
    "intent_prediction": {
      "name": "matricula__horarios",
      "confidence": 0.5608733892440796
    }
  },
  {
    "text": "quiero retirarme algunas asginaturas y quiero saber las fechas",
    "intent": "retiro_parcial__fechas",
    "intent_prediction": {
      "name": "matricula__cronograma",
      "confidence": 0.3837299942970276
    }
  },
  {
    "text": "Hola, quisiera retirarme de un curso me podria decir hasta cuando se habilitara en el sistema ?",
    "intent": "retiro_parcial__fechas",
    "intent_prediction": {
      "name": "retiro_parcial__procedimiento",
      "confidence": 0.5290490388870239
    }
  },
  {
    "text": "deseo realizar el retiro paracial de varios curso como procedo",
    "intent": "retiro_parcial__procedimiento",
    "intent_prediction": {
      "name": "retiro_total__procedimiento",
      "confidence": 0.4202105700969696
    }
  },
  {
    "text": "Buenas tardes, actualemte estoy llevando un solo curso pero por motivos de fuerza mayor deseo retirarme pero el sistema no me lo permite, que puedo hacer",
    "intent": "retiro_parcial__unico_curso",
    "intent_prediction": {
      "name": "retiro_parcial__procedimiento",
      "confidence": 0.35109150409698486
    }
  },
  {
    "text": "Es posible retirarme de 2 cursos si estoy llevando 3?",
    "intent": "retiro_parcial__maximo_cursos",
    "intent_prediction": {
      "name": "retiro_parcial__cursos_repetidos",
      "confidence": 0.251495897769928
    }
  },
  {
    "text": "puedo retirarme de 2 cursos?",
    "intent": "retiro_parcial__maximo_cursos",
    "intent_prediction": {
      "name": "retiro_total__procedimiento",
      "confidence": 0.39165928959846497
    }
  },
  {
    "text": "una duda porfavor existe algun modelo o formato para la solicutud de retiro total",
    "intent": "retiro_total__formato_solicitud",
    "intent_prediction": {
      "name": "retiro_total__procedimiento",
      "confidence": 0.46932467818260193
    }
  },
  {
    "text": "El retiro total es presencial?",
    "intent": "retiro_total__procedimiento",
    "intent_prediction": {
      "name": "retiro_total__motivos_procede",
      "confidence": 0.441221684217453
    }
  },
  {
    "text": "El retiro total se hace virtual?",
    "intent": "retiro_total__procedimiento",
    "intent_prediction": {
      "name": "retiro_total__fechas",
      "confidence": 0.8077936768531799
    }
  },
  {
    "text": "Quiero hacer el retiro total de mis cursos del presente ciclo, quiero saber que documentos se necesitan presentar y que me asegure que no voy a perder mi vacante y que pueda retomar de nuevo las clases en el siguiente ciclo.",
    "intent": "retiro_total__procedimiento",
    "intent_prediction": {
      "name": "retiro_parcial__maximo_cursos",
      "confidence": 0.545592725276947
    }
  },
  {
    "text": "quiero hacer la reserva de matricula, hasta que dia puedo enviar la solicitud ?",
    "intent": "reserva_matricula__fechas",
    "intent_prediction": {
      "name": "reserva_matricula__procedimiento",
      "confidence": 0.4586308002471924
    }
  },
  {
    "text": "Buenas noches, el anterior ciclo reserve mi matricula por motivos familiares , este ciclo si quiero matricularme realizo mi matricula como siempre o hay algun tramite que debo hacer ?",
    "intent": "reincorporacion__procedimiento",
    "intent_prediction": {
      "name": "reserva_matricula__procedimiento",
      "confidence": 0.5424870848655701
    }
  },
  {
    "text": "Buenas tardes, el ciclo pasado no pude matricularme asi que reserve mi matricula quisiera saber ahora como puedo matricularme en el ciclo que viene",
    "intent": "reincorporacion__procedimiento",
    "intent_prediction": {
      "name": "reserva_matricula__procedimiento",
      "confidence": 0.8899460434913635
    }
  },
  {
    "text": "tengo una duda quiero reincorpararme el siguiente ciclo pero no se en que fechas debo comenzar el tramite",
    "intent": "reincorporacion__fechas",
    "intent_prediction": {
      "name": "reincorporacion_rezagada__procedimiento",
      "confidence": 0.29314497113227844
    }
  },
  {
    "text": "Puedo retirarme de cursos con repitencias?",
    "intent": "retiro_parcial__cursos_repetidos",
    "intent_prediction": {
      "name": "retiro_parcial__maximo_cursos",
      "confidence": 0.37335091829299927
    }
  },
  {
    "text": "adios",
    "intent": "despedida",
    "intent_prediction": {
      "name": "saludo",
      "confidence": 0.4323563873767853
    }
  },
  {
    "text": "buenas noches",
    "intent": "despedida",
    "intent_prediction": {
      "name": "saludo",
      "confidence": 0.9340730905532837
    }
  },
  {
    "text": "tongo otra consulta",
    "intent": "confirmar_requerir_mas_ayuda",
    "intent_prediction": {
      "name": "saludo",
      "confidence": 0.560110867023468
    }
  },
  {
    "text": "una duda porfavor existe algun modelo o formato para la solicitud",
    "intent": "formato_solicitud",
    "intent_prediction": {
      "name": "reincorporacion__formato_solicitud",
      "confidence": 0.5514735579490662
    }
  },
  {
    "text": "¿Cuál es el proceso de matrícula para un alumno ingresante?",
    "intent": "matricula__procedimiento_alumno_ingresante",
    "intent_prediction": {
      "name": "matricula__procedimiento_alumno_regular",
      "confidence": 0.44303098320961
    }
  },
  {
    "text": "me puede dar las fechas del pago de autoseguro",
    "intent": "pago_autoseguro__fechas",
    "intent_prediction": {
      "name": "pago_autoseguro_procedimiento",
      "confidence": 0.716709554195404
    }
  },
  {
    "text": "tuve problemas con mi internet y no puede matricuarme que debo hacer",
    "intent": "perdida_turno_matricula",
    "intent_prediction": {
      "name": "pago_autoseguro__fuera_fecha",
      "confidence": 0.1800118088722229
    }
  },
  {
    "text": "Hola Aerito, tengo problemas con mi horario actual del curso de Fisica I en la sección B, quiero hacer el cambio a la seccion A",
    "intent": "cambio_seccion",
    "intent_prediction": {
      "name": "horario_curso",
      "confidence": 0.6089335083961487
    }
  },
  {
    "text": "tengo problemas con mi horario actual del curso de Fisica I en la seccion B, quiero hacer el cambio a la seccion A",
    "intent": "cambio_seccion",
    "intent_prediction": {
      "name": "aulas_curso",
      "confidence": 0.5655158758163452
    }
  },
  {
    "text": "puedo retirarme de los 4 cursos que estoy llevando?",
    "intent": "retiro_parcial__maximo_cursos",
    "intent_prediction": {
      "name": "retiro_total__procedimiento",
      "confidence": 0.3244284987449646
    }
  },
  {
    "text": "el posible retirarme de 3 asignaturas distintas",
    "intent": "retiro_parcial__maximo_cursos",
    "intent_prediction": {
      "name": "retiro_parcial__cursos_repetidos",
      "confidence": 0.3332515060901642
    }
  },
  {
    "text": "cuando pudeo presentar mis documentos para el retiro total",
    "intent": "retiro_total__fechas",
    "intent_prediction": {
      "name": "retiro_total__procedimiento",
      "confidence": 0.2414294183254242
    }
  },
  {
    "text": "Hola, tengo que retirarme de todos mis cursos, ¿Cómo podria hacerlo?",
    "intent": "retiro_total__procedimiento",
    "intent_prediction": {
      "name": "retiro_parcial__procedimiento",
      "confidence": 0.4194139540195465
    }
  },
  {
    "text": "Buenas noches, quisiera saber como puedo hacer una reserva de matricula y ¿Hasta cuándo tengo plazo para presentar mi solicitud? ya que este ciclo que viene no podré llevarlo bien por motivos de trabajo.",
    "intent": "reserva_matricula__procedimiento",
    "intent_prediction": {
      "name": "reincorporacion__procedimiento",
      "confidence": 0.30712077021598816
    }
  },
  {
    "text": "que proceso debo seguir para que se me habilite mi matricula dando que reserve mi matricula el ciclo pasado",
    "intent": "reincorporacion__procedimiento",
    "intent_prediction": {
      "name": "reserva_matricula__procedimiento",
      "confidence": 0.29720339179039
    }
  },
  {
    "text": "como debe ser la solictud de reincorporacion ?",
    "intent": "reincorporacion__formato_solicitud",
    "intent_prediction": {
      "name": "reincorporacion__fechas",
      "confidence": 0.33372142910957336
    }
  },
  {
    "text": "donde un encontra un modelo o formato para esta solicitud",
    "intent": "constancia_de_notas__formato_solicitud",
    "intent_prediction": {
      "name": "formato_solicitud",
      "confidence": 0.7742470502853394
    }
  },
  {
    "text": "me puedo facilitar un modelo para la solicitud de constancia de notas si la hubiera",
    "intent": "constancia_de_notas__formato_solicitud",
    "intent_prediction": {
      "name": "constancia_matricula__formato_solicitud",
      "confidence": 0.26785367727279663
    }
  },
  {
    "text": "Si he repetido un curso en el ciclo paso puedo retirarme en este ciclo de este curso?",
    "intent": "retiro_parcial__cursos_repetidos",
    "intent_prediction": {
      "name": "retiro_parcial__unico_curso",
      "confidence": 0.45118123292922974
    }
  },
  {
    "text": "El curso de Fisica I en la seccion b en que aula se esta dictando?",
    "intent": "aulas_curso",
    "intent_prediction": {
      "name": "horario_curso",
      "confidence": 0.5892614126205444
    }
  },
  {
    "text": "chau",
    "intent": "despedida",
    "intent_prediction": {
      "name": "saludo",
      "confidence": 0.8771980404853821
    }
  },
  {
    "text": "buenas noches",
    "intent": "saludo",
    "intent_prediction": {
      "name": "despedida",
      "confidence": 0.8660581707954407
    }
  },
  {
    "text": "cual es el formato para la solicitud",
    "intent": "formato_solicitud",
    "intent_prediction": {
      "name": "procedimiento_tramites_fechas",
      "confidence": 0.49672096967697144
    }
  },
  {
    "text": "como realizo mi matricula",
    "intent": "matricula_procedimiento",
    "intent_prediction": {
      "name": "matricula__horarios",
      "confidence": 0.1820664256811142
    }
  },
  {
    "text": "¿Cuál es el proceso de matrícula para un alumno regular?",
    "intent": "matricula__procedimiento_alumno_regular",
    "intent_prediction": {
      "name": "matricula__procedimiento_alumno_ingresante",
      "confidence": 0.453357070684433
    }
  },
  {
    "text": "soy alumno ingresante de fisica me podrias decir cual es el proceso de matricula",
    "intent": "matricula__procedimiento_alumno_ingresante",
    "intent_prediction": {
      "name": "matricula__procedimiento_alumno_regular",
      "confidence": 0.7749990224838257
    }
  },
  {
    "text": "soy ingresante de ciencias de la computación cual es el proceso de matricula",
    "intent": "matricula__procedimiento_alumno_ingresante",
    "intent_prediction": {
      "name": "matricula__procedimiento_alumno_regular",
      "confidence": 0.6459366083145142
    }
  },
  {
    "text": "soy alumno ingresante como realizo mi matricula",
    "intent": "matricula__procedimiento_alumno_ingresante",
    "intent_prediction": {
      "name": "matricula__procedimiento_alumno_regular",
      "confidence": 0.6236119270324707
    }
  },
  {
    "text": "me podria decir como saber mi horario de matricula.",
    "intent": "matricula__horarios",
    "intent_prediction": {
      "name": "matricula__cronograma",
      "confidence": 0.49348869919776917
    }
  },
  {
    "text": "Si recien me acorde que debo pagar el autoseguro antes de la matricula, hasta cuando puedo pagarlo",
    "intent": "pago_autoseguro__fechas",
    "intent_prediction": {
      "name": "pago_autoseguro__fuera_fecha",
      "confidence": 0.5613197088241577
    }
  },
  {
    "text": "Buenas dias es que me han dicho que pague el autoseguro pero no entiendo como",
    "intent": "pago_autoseguro_procedimiento",
    "intent_prediction": {
      "name": "pago_autoseguro__fuera_fecha",
      "confidence": 0.7270494103431702
    }
  },
  {
    "text": "no pude matricularme que debería hacer ahora",
    "intent": "perdida_turno_matricula",
    "intent_prediction": {
      "name": "matricula_rezagada__procedimiento",
      "confidence": 0.5404179692268372
    }
  },
  {
    "text": "¿Hay un límite de cursos para retirarme de modo parcial?",
    "intent": "retiro_parcial__maximo_cursos",
    "intent_prediction": {
      "name": "retiro_parcial__unico_curso",
      "confidence": 0.4051533639431
    }
  },
  {
    "text": "es posible hacer el retiro total de todos los cursos que estoy matricula",
    "intent": "retiro_parcial__maximo_cursos",
    "intent_prediction": {
      "name": "retiro_total__procedimiento",
      "confidence": 0.7709290981292725
    }
  },
  {
    "text": "para solicitar el retiro total debo presentar algun documento que justifique mis motivos?",
    "intent": "retiro_total__requisitos_documentos_justificacion",
    "intent_prediction": {
      "name": "retiro_total__procedimiento",
      "confidence": 0.21578143537044525
    }
  },
  {
    "text": "¿Qué motivos justifican el retiro total de cursos?",
    "intent": "retiro_total__motivos_procede",
    "intent_prediction": {
      "name": "retiro_parcial__fechas",
      "confidence": 0.6357702016830444
    }
  },
  {
    "text": "¿Cuándo procede el retiro total?",
    "intent": "retiro_total__motivos_procede",
    "intent_prediction": {
      "name": "retiro_total__fechas",
      "confidence": 0.7481429576873779
    }
  },
  {
    "text": "quiero solicitar el retiro total me puedes enviar el modelo para la solicitud",
    "intent": "retiro_total__formato_solicitud",
    "intent_prediction": {
      "name": "retiro_total__procedimiento",
      "confidence": 0.908291220664978
    }
  },
  {
    "text": "¿Cómo reservo mi matricula?",
    "intent": "reserva_matricula__procedimiento",
    "intent_prediction": {
      "name": "matricula_procedimiento",
      "confidence": 0.2318311482667923
    }
  },
  {
    "text": "hola, no podre matricula como puedo postergar mi matricula",
    "intent": "reserva_matricula__procedimiento",
    "intent_prediction": {
      "name": "perdida_turno_matricula",
      "confidence": 0.40303388237953186
    }
  },
  {
    "text": "cual es el formato de solicitud para la reserva de matricula ?",
    "intent": "reserva_matricula__formato_solicitud",
    "intent_prediction": {
      "name": "reserva_matricula__procedimiento",
      "confidence": 0.5955839157104492
    }
  },
  {
    "text": "Si ya pasó la fecha de la reincorporación, pasaría a rezagado",
    "intent": "reincorporacion_rezagada__procedimiento",
    "intent_prediction": {
      "name": "pago_autoseguro__fuera_fecha",
      "confidence": 0.3425094783306122
    }
  },
  {
    "text": "cuando debo enviar mi solictud para mi reincorporacion para el siguiente periodo academico",
    "intent": "reincorporacion__fechas",
    "intent_prediction": {
      "name": "reincorporacion__procedimiento",
      "confidence": 0.7578951716423035
    }
  },
  {
    "text": "Puedo retirame de una asginatura que he repetido",
    "intent": "retiro_parcial__cursos_repetidos",
    "intent_prediction": {
      "name": "retiro_parcial__procedimiento",
      "confidence": 0.15956175327301025
    }
  },
  {
    "text": "cuando se dicta el curso de Fisica I?",
    "intent": "horario_curso",
    "intent_prediction": {
      "name": "aulas_curso",
      "confidence": 0.5415237545967102
    }
  },
  {
    "text": "a que hora comienza las clases del curso de biologia?",
    "intent": "horario_curso",
    "intent_prediction": {
      "name": "horario_atencion_aera",
      "confidence": 0.3656739294528961
    }
  },
  {
    "text": "donde puedo encontrar un modelo",
    "intent": "formato_solicitud",
    "intent_prediction": {
      "name": "solicitud_correo_institucional_procedimiento",
      "confidence": 0.43748965859413147
    }
  },
  {
    "text": "soy alumno regular de fisica me podrias decir cual es el proceso de matricula",
    "intent": "matricula__procedimiento_alumno_regular",
    "intent_prediction": {
      "name": "matricula__procedimiento_alumno_ingresante",
      "confidence": 0.7481399774551392
    }
  },
  {
    "text": "he ingresado a la carrera de Quimica en el anterior examen de admisión quisiera que debo hacer para matricularme",
    "intent": "matricula__procedimiento_alumno_ingresante",
    "intent_prediction": {
      "name": "reincorporacion__procedimiento",
      "confidence": 0.6343745589256287
    }
  },
  {
    "text": "Buenas tardes, como puedo saber el día de mi matrícula",
    "intent": "matricula__cronograma",
    "intent_prediction": {
      "name": "matricula__horarios",
      "confidence": 0.6873863935470581
    }
  },
  {
    "text": "Buen día, a que hora inicia la matrícula",
    "intent": "matricula__horarios",
    "intent_prediction": {
      "name": "matricula__cronograma",
      "confidence": 0.46398842334747314
    }
  },
  {
    "text": "Buen día, necesito saber cuando me toca matricularme",
    "intent": "matricula__horarios",
    "intent_prediction": {
      "name": "matricula__cronograma",
      "confidence": 0.8144226670265198
    }
  },
  {
    "text": "buenos dias, no pude matricularme en la fecha que me correspondía, cual es el procedimiento para rezagado",
    "intent": "matricula_rezagada__procedimiento",
    "intent_prediction": {
      "name": "perdida_turno_matricula",
      "confidence": 0.8724071979522705
    }
  },
  {
    "text": "no pude matricularme a tiempo cual es procedimiento para la matricula rezagada",
    "intent": "matricula_rezagada__procedimiento",
    "intent_prediction": {
      "name": "perdida_turno_matricula",
      "confidence": 0.6407148838043213
    }
  },
  {
    "text": "Hola, he querido retirarme de un curso pero me parece que un no esta habilitado cuando se habilitara el retiro parcial?",
    "intent": "retiro_parcial__fechas",
    "intent_prediction": {
      "name": "retiro_parcial__procedimiento",
      "confidence": 0.8270992040634155
    }
  },
  {
    "text": "¿El retiro parcial aplica para los estudiantes que llevan solo un curso?",
    "intent": "retiro_parcial__unico_curso",
    "intent_prediction": {
      "name": "retiro_parcial__maximo_cursos",
      "confidence": 0.7325005531311035
    }
  },
  {
    "text": "cuando puedo hacer un retiro total",
    "intent": "retiro_total__fechas",
    "intent_prediction": {
      "name": "retiro_total__procedimiento",
      "confidence": 0.2236536592245102
    }
  },
  {
    "text": "debo justificar mis motivos para solicitar mi retiro total?",
    "intent": "retiro_total__requisitos_documentos_justificacion",
    "intent_prediction": {
      "name": "retiro_total__motivos_procede",
      "confidence": 0.6084510087966919
    }
  },
  {
    "text": "¿Cuál es el modelo para la solicitud de retiro total?",
    "intent": "retiro_total__formato_solicitud",
    "intent_prediction": {
      "name": "retiro_total__procedimiento",
      "confidence": 0.3913510739803314
    }
  },
  {
    "text": "Quiero retirarme del ciclo",
    "intent": "retiro_total__procedimiento",
    "intent_prediction": {
      "name": "retiro_parcial__procedimiento",
      "confidence": 0.24875754117965698
    }
  },
  {
    "text": "Buenos días, me veo obligada de retirarme de todos los cursos por motivos de trabajo, cual es el procedimiento por favor",
    "intent": "retiro_total__procedimiento",
    "intent_prediction": {
      "name": "retiro_parcial__procedimiento",
      "confidence": 0.8580412864685059
    }
  },
  {
    "text": "Hola ciencito, queria consultarte lo que pasa es que por temas familiares este ciclo estaba pensando no matricular que debo hacer",
    "intent": "reserva_matricula__procedimiento",
    "intent_prediction": {
      "name": "reincorporacion__procedimiento",
      "confidence": 0.4235661029815674
    }
  },
  {
    "text": "aun puedo enviar la solicitud de reserva de matricula ?",
    "intent": "reserva_matricula__fechas",
    "intent_prediction": {
      "name": "reserva_matricula__procedimiento",
      "confidence": 0.8815174102783203
    }
  },
  {
    "text": "Buenas tardes, Realice la Reserva de Matrícula el periodo pasado, que me corresponde hacer para matricularme este periodo",
    "intent": "reincorporacion__procedimiento",
    "intent_prediction": {
      "name": "reserva_matricula__procedimiento",
      "confidence": 0.8949511647224426
    }
  },
  {
    "text": "he dejado de estudiar hace año, como podria matricularme en el siguiente ciclo",
    "intent": "reincorporacion__procedimiento",
    "intent_prediction": {
      "name": "perdida_turno_matricula",
      "confidence": 0.6805880665779114
    }
  },
  {
    "text": "una consulta, es que fechas deberia solicitar mi reincorparacion",
    "intent": "reincorporacion__fechas",
    "intent_prediction": {
      "name": "reincorporacion__procedimiento",
      "confidence": 0.841361939907074
    }
  },
  {
    "text": "tengo una consulta desde que fecha ya puedo iniciar el tramite para mi reicorporacion en el siguiente ciclo",
    "intent": "reincorporacion__fechas",
    "intent_prediction": {
      "name": "reincorporacion__procedimiento",
      "confidence": 0.7298014163970947
    }
  },
  {
    "text": "estoy buscando el modelo de la solitud de reincorporacion y no lo encuetro puedes decirme donde esta ?",
    "intent": "reincorporacion__formato_solicitud",
    "intent_prediction": {
      "name": "reincorporacion__procedimiento",
      "confidence": 0.5753574967384338
    }
  },
  {
    "text": "es posible retirase de cursos con repitencias ?",
    "intent": "retiro_parcial__cursos_repetidos",
    "intent_prediction": {
      "name": "retiro_parcial__maximo_cursos",
      "confidence": 0.6612401008605957
    }
  },
  {
    "text": "quisero hacer el retiro de un curso que estoy llevando por segunda ver es posible?",
    "intent": "retiro_parcial__cursos_repetidos",
    "intent_prediction": {
      "name": "retiro_parcial__procedimiento",
      "confidence": 0.40564626455307007
    }
  },
  {
    "text": "dime que aula en que aula es el curso de calculo numerico i?",
    "intent": "aulas_curso",
    "intent_prediction": {
      "name": "horario_curso",
      "confidence": 0.7507854104042053
    }
  },
  {
    "text": "si una mas",
    "intent": "confirmar_requerir_mas_ayuda",
    "intent_prediction": {
      "name": "saludo",
      "confidence": 0.5328164100646973
    }
  },
  {
    "text": "si hasta que dia lo puedo pagar",
    "intent": "pago_fechas",
    "intent_prediction": {
      "name": "pago_autoseguro__fechas",
      "confidence": 0.5050889849662781
    }
  },
  {
    "text": "como alumno regular que pagos debo hacer para realizar la matricula",
    "intent": "matricula__procedimiento_alumno_regular",
    "intent_prediction": {
      "name": "matricula_procedimiento",
      "confidence": 0.2702694237232208
    }
  },
  {
    "text": "Soy ingresante como es el proceso de matricula",
    "intent": "matricula__procedimiento_alumno_ingresante",
    "intent_prediction": {
      "name": "matricula__procedimiento_alumno_regular",
      "confidence": 0.52814120054245
    }
  },
  {
    "text": "de mas debo hacer para obtener mi carnet universitario?",
    "intent": "carnet_universitario__solicitud",
    "intent_prediction": {
      "name": "retiro_parcial__maximo_cursos",
      "confidence": 0.1518205851316452
    }
  },
  {
    "text": "Hola quiero saber cuando se hara la matricula en el siguiente ciclo",
    "intent": "matricula__cronograma",
    "intent_prediction": {
      "name": "matricula__horarios",
      "confidence": 0.5673373341560364
    }
  },
  {
    "text": "donde puedo encontrar los horarios de la matricula?",
    "intent": "matricula__horarios",
    "intent_prediction": {
      "name": "cursos_horarios",
      "confidence": 0.6607152223587036
    }
  },
  {
    "text": "que pasa si no pago el autoseguro a tiempo",
    "intent": "pago_autoseguro_procedimiento",
    "intent_prediction": {
      "name": "pago_autoseguro__fuera_fecha",
      "confidence": 0.937400221824646
    }
  },
  {
    "text": "no puede matricularme por problemas de internet paso a matricula rezagada entonces ?",
    "intent": "perdida_turno_matricula",
    "intent_prediction": {
      "name": "matricula_rezagada__procedimiento",
      "confidence": 0.6794708967208862
    }
  },
  {
    "text": "Buenas, quisiera saber si aún se puede hacer el retiro parcial, el motivo es que estoy con tratamiento psiquiátrico y me recomendaron que me retire de algunos cursos",
    "intent": "retiro_parcial__fechas",
    "intent_prediction": {
      "name": "retiro_parcial__procedimiento",
      "confidence": 0.9671985507011414
    }
  },
  {
    "text": "Hola Aerito, hasta que dias puedo realizar el retiro parcial",
    "intent": "retiro_parcial__fechas",
    "intent_prediction": {
      "name": "retiro_total__fechas",
      "confidence": 0.8757733106613159
    }
  },
  {
    "text": "¿Se requiere documentos para justificar el retiro total?",
    "intent": "retiro_total__requisitos_documentos_justificacion",
    "intent_prediction": {
      "name": "retiro_total__motivos_procede",
      "confidence": 0.8323426246643066
    }
  },
  {
    "text": "Debo presentar documentos para justificar los motivos de retiro total?",
    "intent": "retiro_total__requisitos_documentos_justificacion",
    "intent_prediction": {
      "name": "retiro_total__motivos_procede",
      "confidence": 0.5056093335151672
    }
  },
  {
    "text": "que motivos de fuerza mayor permiten el retiro total",
    "intent": "retiro_total__motivos_procede",
    "intent_prediction": {
      "name": "retiro_total__fechas",
      "confidence": 0.6974361538887024
    }
  },
  {
    "text": "¿Cuáles son los pasos para solicitar el retito total?",
    "intent": "retiro_total__procedimiento",
    "intent_prediction": {
      "name": "retiro_total__formato_solicitud",
      "confidence": 0.3762851059436798
    }
  },
  {
    "text": "como puedo solcitar el retiro de todas las asignaturas que estoy llevando",
    "intent": "retiro_total__procedimiento",
    "intent_prediction": {
      "name": "retiro_parcial__maximo_cursos",
      "confidence": 0.5285820364952087
    }
  },
  {
    "text": "Puedo retirarme de todos los cursos?",
    "intent": "retiro_total__procedimiento",
    "intent_prediction": {
      "name": "retiro_parcial__maximo_cursos",
      "confidence": 0.7936328649520874
    }
  },
  {
    "text": "si tambien quisiera que debaria de hacer luego de la reserva de matricula para reincoporarme el siguiente ciclo",
    "intent": "reincorporacion__procedimiento",
    "intent_prediction": {
      "name": "reincorporacion__fechas",
      "confidence": 0.2191161811351776
    }
  },
  {
    "text": "Necesitaría mayor información de como es el procedimiento de reincorporación por favor",
    "intent": "reincorporacion__procedimiento",
    "intent_prediction": {
      "name": "reincorporacion__formato_solicitud",
      "confidence": 0.48695045709609985
    }
  },
  {
    "text": "Realice la Reserva de Matrícula el periodo pasado, que me corresponde hacer para matricularme este periodo",
    "intent": "reincorporacion__procedimiento",
    "intent_prediction": {
      "name": "reserva_matricula__procedimiento",
      "confidence": 0.8705275654792786
    }
  },
  {
    "text": "cuando puedo enviar mi solicitud para mi reincorporacion",
    "intent": "reincorporacion__fechas",
    "intent_prediction": {
      "name": "reincorporacion__procedimiento",
      "confidence": 0.5659146308898926
    }
  },
  {
    "text": "quisiera hacer el retiro de un curso pero lo he desaprobado el ciclo, es posible o no procede?",
    "intent": "retiro_parcial__cursos_repetidos",
    "intent_prediction": {
      "name": "retiro_parcial__procedimiento",
      "confidence": 0.570895254611969
    }
  },
  {
    "text": "quiero saber el aula donde se dicta el curso de fisica iii?",
    "intent": "aulas_curso",
    "intent_prediction": {
      "name": "horario_curso",
      "confidence": 0.684053361415863
    }
  },
  {
    "text": "no encuentro el laboratorio donde se dicta física I sección b",
    "intent": "aulas_curso",
    "intent_prediction": {
      "name": "ubicacion_aulas",
      "confidence": 0.3199404776096344
    }
  }
]